setup.py
thorin/run_tests.py
thorin/server.py
thorin.egg-info/PKG-INFO
thorin.egg-info/SOURCES.txt
thorin.egg-info/dependency_links.txt
thorin.egg-info/requires.txt
thorin.egg-info/top_level.txt
thorin/thorin_tests/thorin_tests.py