Metadata-Version: 1.1
Name: thorin
Version: 1.0.11
Summary: Thorin - Web Framework
Home-page: https://github.com/philsitumorang/thorin
Author: Phil Situmorang
Author-email: philmsk@gmail.com
License: MIT License
Download-URL: https://github.com/philsitumorang/thorin/archive/master.zip
Keywords: thorin
Platform: UNKNOWN
Classifier: Environment :: Web Environment
Classifier: Intended Audience :: Developers
Classifier: Programming Language :: Python
Requires: python (>= 3.0)
